{"objects":[{"rx":0,"ry":0,"top":0,"fill":"rgba(12, 16, 14, 0.65)","left":0,"type":"Rect","angle":0,"flipX":false,"flipY":false,"skewX":0,"skewY":0,"width":760,"height":434,"scaleX":1,"scaleY":1,"shadow":null,"stroke":null,"opacity":1,"originX":"left","originY":"top","version":"6.9.1","visible":true,"fillRule":"nonzero","paintFirst":"fill","strokeWidth":1,"strokeLineCap":"butt","strokeUniform":false,"strokeLineJoin":"miter","backgroundColor":"","strokeDashArray":null,"strokeDashOffset":0,"strokeMiterLimit":4,"globalCompositeOperation":"source-over"},{"rx":0,"ry":0,"top":50,"fill":"#dfba73","left":40,"type":"Rect","angle":0,"flipX":false,"flipY":false,"skewX":0,"skewY":0,"width":2,"height":334,"scaleX":1,"scaleY":1,"shadow":null,"stroke":null,"opacity":0.4,"originX":"left","originY":"top","version":"6.9.1","visible":true,"fillRule":"nonzero","paintFirst":"fill","strokeWidth":1,"strokeLineCap":"butt","strokeUniform":false,"strokeLineJoin":"miter","backgroundColor":"","strokeDashArray":null,"strokeDashOffset":0,"strokeMiterLimit":4,"globalCompositeOperation":"source-over"},{"rx":0,"ry":0,"top":50,"fill":"#dfba73","left":500,"type":"Rect","angle":0,"flipX":false,"flipY":false,"skewX":0,"skewY":0,"width":210,"height":1,"scaleX":1,"scaleY":1,"shadow":null,"stroke":null,"opacity":0.3,"originX":"left","originY":"top","version":"6.9.1","visible":true,"fillRule":"nonzero","paintFirst":"fill","strokeWidth":1,"strokeLineCap":"butt","strokeUniform":false,"strokeLineJoin":"miter","backgroundColor":"","strokeDashArray":null,"strokeDashOffset":0,"strokeMiterLimit":4,"globalCompositeOperation":"source-over"},{"rx":0,"ry":0,"top":50,"fill":"#dfba73","left":710,"type":"Rect","angle":0,"flipX":false,"flipY":false,"skewX":0,"skewY":0,"width":1,"height":150,"scaleX":1,"scaleY":1,"shadow":null,"stroke":null,"opacity":0.3,"originX":"left","originY":"top","version":"6.9.1","visible":true,"fillRule":"nonzero","paintFirst":"fill","strokeWidth":1,"strokeLineCap":"butt","strokeUniform":false,"strokeLineJoin":"miter","backgroundColor":"","strokeDashArray":null,"strokeDashOffset":0,"strokeMiterLimit":4,"globalCompositeOperation":"source-over"},{"top":60,"fill":"#ffffff","left":110,"text":"AURA SANCTUARY","type":"IText","angle":0,"flipX":false,"flipY":false,"skewX":0,"skewY":0,"width":206.4004,"height":24.86,"scaleX":1,"scaleY":1,"shadow":null,"stroke":null,"styles":[],"opacity":1,"originX":"left","originY":"top","rmpRole":"companyName","version":"6.9.1","visible":true,"fillRule":"nonzero","fontSize":22,"overline":false,"pathSide":"left","direction":"ltr","fontStyle":"normal","pathAlign":"baseline","textAlign":"left","underline":false,"fontFamily":"Playfair Display","fontWeight":"bold","lineHeight":1.16,"paintFirst":"fill","charSpacing":0,"linethrough":false,"strokeWidth":1,"strokeLineCap":"butt","strokeUniform":false,"strokeLineJoin":"miter","backgroundColor":"","pathStartOffset":0,"strokeDashArray":null,"strokeDashOffset":0,"strokeMiterLimit":4,"textBackgroundColor":"","textDecorationThickness":66.667,"globalCompositeOperation":"source-over"},{"top":160,"fill":"#ffffff","left":60,"text":"Elena Rostova","type":"IText","angle":0,"flipX":false,"flipY":false,"skewX":0,"skewY":0,"width":196.4531,"height":36.16,"scaleX":1,"scaleY":1,"shadow":null,"stroke":null,"styles":[],"opacity":1,"originX":"left","originY":"top","rmpRole":"name","version":"6.9.1","visible":true,"fillRule":"nonzero","fontSize":32,"overline":false,"pathSide":"left","direction":"ltr","fontStyle":"normal","pathAlign":"baseline","textAlign":"left","underline":false,"fontFamily":"Playfair Display","fontWeight":"bold","lineHeight":1.16,"paintFirst":"fill","charSpacing":0,"linethrough":false,"strokeWidth":1,"strokeLineCap":"butt","strokeUniform":false,"strokeLineJoin":"miter","backgroundColor":"","pathStartOffset":0,"strokeDashArray":null,"strokeDashOffset":0,"strokeMiterLimit":4,"textBackgroundColor":"","textDecorationThickness":66.667,"globalCompositeOperation":"source-over"},{"top":205,"fill":"#dfba73","left":60,"text":"FOUNDER & CREATIVE DIRECTOR","type":"IText","angle":0,"flipX":false,"flipY":false,"skewX":0,"skewY":0,"width":175.6262,"height":12.43,"scaleX":1,"scaleY":1,"shadow":null,"stroke":null,"styles":[],"opacity":1,"originX":"left","originY":"top","rmpRole":"title","version":"6.9.1","visible":true,"fillRule":"nonzero","fontSize":11,"overline":false,"pathSide":"left","direction":"ltr","fontStyle":"normal","pathAlign":"baseline","textAlign":"left","underline":false,"fontFamily":"Raleway","fontWeight":"normal","lineHeight":1.16,"paintFirst":"fill","charSpacing":0,"linethrough":false,"strokeWidth":1,"strokeLineCap":"butt","strokeUniform":false,"strokeLineJoin":"miter","backgroundColor":"","pathStartOffset":0,"strokeDashArray":null,"strokeDashOffset":0,"strokeMiterLimit":4,"textBackgroundColor":"","textDecorationThickness":66.667,"globalCompositeOperation":"source-over"},{"top":325,"fill":"#e2e8f0","left":60,"text":"www.aurasanctuary.com","type":"IText","angle":0,"flipX":false,"flipY":false,"skewX":0,"skewY":0,"width":176.6722,"height":14.69,"scaleX":1,"scaleY":1,"shadow":null,"stroke":null,"styles":[],"opacity":1,"originX":"left","originY":"top","rmpRole":"url","version":"6.9.1","visible":true,"fillRule":"nonzero","fontSize":13,"overline":false,"pathSide":"left","direction":"ltr","fontStyle":"normal","pathAlign":"baseline","textAlign":"left","underline":false,"fontFamily":"Raleway","fontWeight":"normal","lineHeight":1.16,"paintFirst":"fill","charSpacing":0,"linethrough":false,"strokeWidth":1,"strokeLineCap":"butt","strokeUniform":false,"strokeLineJoin":"miter","backgroundColor":"","pathStartOffset":0,"strokeDashArray":null,"strokeDashOffset":0,"strokeMiterLimit":4,"textBackgroundColor":"","textDecorationThickness":66.667,"globalCompositeOperation":"source-over"},{"top":295,"fill":"#e2e8f0","left":60,"text":"T: +1 (555) 234-5678","type":"IText","angle":0,"flipX":false,"flipY":false,"skewX":0,"skewY":0,"width":117.7016,"height":14.69,"scaleX":1,"scaleY":1,"shadow":null,"stroke":null,"styles":[],"opacity":1,"originX":"left","originY":"top","rmpRole":"phone","version":"6.9.1","visible":true,"fillRule":"nonzero","fontSize":13,"overline":false,"pathSide":"left","direction":"ltr","fontStyle":"normal","pathAlign":"baseline","textAlign":"left","underline":false,"fontFamily":"Raleway","fontWeight":"normal","lineHeight":1.16,"paintFirst":"fill","charSpacing":0,"linethrough":false,"strokeWidth":1,"strokeLineCap":"butt","strokeUniform":false,"strokeLineJoin":"miter","backgroundColor":"","pathStartOffset":0,"strokeDashArray":null,"strokeDashOffset":0,"strokeMiterLimit":4,"textBackgroundColor":"","textDecorationThickness":66.667,"globalCompositeOperation":"source-over"},{"src":"/storage/brand/logo-placeholder.webp","top":216.99,"left":410.9,"type":"Image","width":512,"height":279,"scaleX":0.4102,"scaleY":0.4102,"originX":"center","originY":"center","rmpRole":"logo","version":"6.0.0","crossOrigin":"anonymous"}],"version":"6.9.1","background":"#0c100e"}