{"objects":[{"rx":0,"ry":0,"top":0,"fill":"#1E3A34","left":0,"type":"Rect","angle":0,"flipX":false,"flipY":false,"skewX":0,"skewY":0,"width":280,"height":434,"scaleX":1,"scaleY":1,"shadow":null,"stroke":null,"opacity":1,"originX":"left","originY":"top","version":"6.9.1","visible":true,"fillRule":"nonzero","paintFirst":"fill","strokeWidth":1,"strokeLineCap":"butt","strokeUniform":false,"strokeLineJoin":"miter","backgroundColor":"","strokeDashArray":null,"strokeDashOffset":0,"strokeMiterLimit":4,"globalCompositeOperation":"source-over"},{"rx":0,"ry":0,"top":0,"fill":"#8A2F16","left":280,"type":"Rect","angle":0,"flipX":false,"flipY":false,"skewX":0,"skewY":0,"width":6,"height":434,"scaleX":1,"scaleY":1,"shadow":null,"stroke":null,"opacity":1,"originX":"left","originY":"top","version":"6.9.1","visible":true,"fillRule":"nonzero","paintFirst":"fill","strokeWidth":1,"strokeLineCap":"butt","strokeUniform":false,"strokeLineJoin":"miter","backgroundColor":"","strokeDashArray":null,"strokeDashOffset":0,"strokeMiterLimit":4,"globalCompositeOperation":"source-over"},{"rx":0,"ry":0,"top":-40,"fill":"#8A2F16","left":680,"type":"Rect","angle":0,"flipX":false,"flipY":false,"skewX":0,"skewY":0,"width":120,"height":120,"scaleX":1,"scaleY":1,"shadow":null,"stroke":null,"opacity":0.12,"originX":"left","originY":"top","version":"6.9.1","visible":true,"fillRule":"nonzero","paintFirst":"fill","strokeWidth":1,"strokeLineCap":"butt","strokeUniform":false,"strokeLineJoin":"miter","backgroundColor":"","strokeDashArray":null,"strokeDashOffset":0,"strokeMiterLimit":4,"globalCompositeOperation":"source-over"},{"rx":0,"ry":0,"top":185,"fill":"#8A2F16","left":330,"type":"Rect","angle":0,"flipX":false,"flipY":false,"skewX":0,"skewY":0,"width":45,"height":3,"scaleX":1,"scaleY":1,"shadow":null,"stroke":null,"opacity":1,"originX":"left","originY":"top","version":"6.9.1","visible":true,"fillRule":"nonzero","paintFirst":"fill","strokeWidth":1,"strokeLineCap":"butt","strokeUniform":false,"strokeLineJoin":"miter","backgroundColor":"","strokeDashArray":null,"strokeDashOffset":0,"strokeMiterLimit":4,"globalCompositeOperation":"source-over"},{"top":235,"fill":"#F4EAE1","left":65,"text":"VILLA & CO.","type":"IText","angle":0,"flipX":false,"flipY":false,"skewX":0,"skewY":0,"width":128.3121,"height":27.12,"scaleX":1,"scaleY":1,"shadow":null,"stroke":null,"styles":[],"opacity":1,"originX":"left","originY":"top","rmpRole":"companyName","version":"6.9.1","visible":true,"fillRule":"nonzero","fontSize":24,"overline":false,"pathSide":"left","direction":"ltr","fontStyle":"normal","pathAlign":"baseline","textAlign":"left","underline":false,"fontFamily":"League Spartan","fontWeight":"bold","lineHeight":1.16,"paintFirst":"fill","charSpacing":0,"linethrough":false,"strokeWidth":1,"strokeLineCap":"butt","strokeUniform":false,"strokeLineJoin":"miter","backgroundColor":"","pathStartOffset":0,"strokeDashArray":null,"strokeDashOffset":0,"strokeMiterLimit":4,"textBackgroundColor":"","textDecorationThickness":66.667,"globalCompositeOperation":"source-over"},{"top":110,"fill":"#1E3A34","left":330,"text":"Julian Vance","type":"IText","angle":0,"flipX":false,"flipY":false,"skewX":0,"skewY":0,"width":179.1147,"height":36.16,"scaleX":1,"scaleY":1,"shadow":null,"stroke":null,"styles":[],"opacity":1,"originX":"left","originY":"top","rmpRole":"name","version":"6.9.1","visible":true,"fillRule":"nonzero","fontSize":32,"overline":false,"pathSide":"left","direction":"ltr","fontStyle":"normal","pathAlign":"baseline","textAlign":"left","underline":false,"fontFamily":"League Spartan","fontWeight":"bold","lineHeight":1.16,"paintFirst":"fill","charSpacing":0,"linethrough":false,"strokeWidth":1,"strokeLineCap":"butt","strokeUniform":false,"strokeLineJoin":"miter","backgroundColor":"","pathStartOffset":0,"strokeDashArray":null,"strokeDashOffset":0,"strokeMiterLimit":4,"textBackgroundColor":"","textDecorationThickness":66.667,"globalCompositeOperation":"source-over"},{"top":155,"fill":"#8A2F16","left":330,"text":"LEAD ACQUISITION PARTNER","type":"IText","angle":0,"flipX":false,"flipY":false,"skewX":0,"skewY":0,"width":185.7841,"height":13.56,"scaleX":1,"scaleY":1,"shadow":null,"stroke":null,"styles":[],"opacity":1,"originX":"left","originY":"top","rmpRole":"title","version":"6.9.1","visible":true,"fillRule":"nonzero","fontSize":12,"overline":false,"pathSide":"left","direction":"ltr","fontStyle":"normal","pathAlign":"baseline","textAlign":"left","underline":false,"fontFamily":"Montserrat","fontWeight":"bold","lineHeight":1.16,"paintFirst":"fill","charSpacing":0,"linethrough":false,"strokeWidth":1,"strokeLineCap":"butt","strokeUniform":false,"strokeLineJoin":"miter","backgroundColor":"","pathStartOffset":0,"strokeDashArray":null,"strokeDashOffset":0,"strokeMiterLimit":4,"textBackgroundColor":"","textDecorationThickness":66.667,"globalCompositeOperation":"source-over"},{"top":215,"fill":"#1E3A34","left":330,"text":"www.villaco.re","type":"IText","angle":0,"flipX":false,"flipY":false,"skewX":0,"skewY":0,"width":113.2951,"height":15.82,"scaleX":1,"scaleY":1,"shadow":null,"stroke":null,"styles":[],"opacity":1,"originX":"left","originY":"top","rmpRole":"url","version":"6.9.1","visible":true,"fillRule":"nonzero","fontSize":14,"overline":false,"pathSide":"left","direction":"ltr","fontStyle":"normal","pathAlign":"baseline","textAlign":"left","underline":false,"fontFamily":"Montserrat","fontWeight":"normal","lineHeight":1.16,"paintFirst":"fill","charSpacing":0,"linethrough":false,"strokeWidth":1,"strokeLineCap":"butt","strokeUniform":false,"strokeLineJoin":"miter","backgroundColor":"","pathStartOffset":0,"strokeDashArray":null,"strokeDashOffset":0,"strokeMiterLimit":4,"textBackgroundColor":"","textDecorationThickness":66.667,"globalCompositeOperation":"source-over"},{"top":245,"fill":"#1E3A34","left":330,"text":"+1 (555) 382-9102","type":"IText","angle":0,"flipX":false,"flipY":false,"skewX":0,"skewY":0,"width":113.862,"height":15.82,"scaleX":1,"scaleY":1,"shadow":null,"stroke":null,"styles":[],"opacity":1,"originX":"left","originY":"top","rmpRole":"phone","version":"6.9.1","visible":true,"fillRule":"nonzero","fontSize":14,"overline":false,"pathSide":"left","direction":"ltr","fontStyle":"normal","pathAlign":"baseline","textAlign":"left","underline":false,"fontFamily":"Montserrat","fontWeight":"normal","lineHeight":1.16,"paintFirst":"fill","charSpacing":0,"linethrough":false,"strokeWidth":1,"strokeLineCap":"butt","strokeUniform":false,"strokeLineJoin":"miter","backgroundColor":"","pathStartOffset":0,"strokeDashArray":null,"strokeDashOffset":0,"strokeMiterLimit":4,"textBackgroundColor":"","textDecorationThickness":66.667,"globalCompositeOperation":"source-over"},{"src":"/storage/brand/logo-placeholder.webp","top":175,"left":100,"type":"Image","width":512,"height":279,"scaleX":0.1953,"scaleY":0.1953,"originX":"center","originY":"center","rmpRole":"logo","version":"6.0.0","crossOrigin":"anonymous"}],"version":"6.9.1","background":"#F4EAE1"}