{"objects":[{"rx":0,"ry":0,"top":40,"fill":"#10B981","left":379,"type":"Rect","angle":0,"flipX":false,"flipY":false,"skewX":0,"skewY":0,"width":2,"height":354,"scaleX":1,"scaleY":1,"shadow":null,"stroke":null,"opacity":0.15,"originX":"left","originY":"top","version":"6.9.1","visible":true,"fillRule":"nonzero","paintFirst":"fill","strokeWidth":1,"strokeLineCap":"butt","strokeUniform":false,"strokeLineJoin":"miter","backgroundColor":"","strokeDashArray":null,"strokeDashOffset":0,"strokeMiterLimit":4,"globalCompositeOperation":"source-over"},{"rx":0,"ry":0,"top":165,"fill":"#10B981","left":330,"type":"Rect","angle":0,"flipX":false,"flipY":false,"skewX":0,"skewY":0,"width":100,"height":3,"scaleX":1,"scaleY":1,"shadow":null,"stroke":null,"opacity":1,"originX":"left","originY":"top","version":"6.9.1","visible":true,"fillRule":"nonzero","paintFirst":"fill","strokeWidth":1,"strokeLineCap":"butt","strokeUniform":false,"strokeLineJoin":"miter","backgroundColor":"","strokeDashArray":null,"strokeDashOffset":0,"strokeMiterLimit":4,"globalCompositeOperation":"source-over"},{"rx":0,"ry":0,"top":422,"fill":"#10B981","left":0,"type":"Rect","angle":0,"flipX":false,"flipY":false,"skewX":0,"skewY":0,"width":760,"height":12,"scaleX":1,"scaleY":1,"shadow":null,"stroke":null,"opacity":1,"originX":"left","originY":"top","version":"6.9.1","visible":true,"fillRule":"nonzero","paintFirst":"fill","strokeWidth":1,"strokeLineCap":"butt","strokeUniform":false,"strokeLineJoin":"miter","backgroundColor":"","strokeDashArray":null,"strokeDashOffset":0,"strokeMiterLimit":4,"globalCompositeOperation":"source-over"},{"top":118,"fill":"#ECFDF5","left":180,"text":"VERDANT EDGE","type":"IText","angle":0,"flipX":false,"flipY":false,"skewX":0,"skewY":0,"width":177.8574,"height":31.64,"scaleX":1,"scaleY":1,"shadow":null,"stroke":null,"styles":[],"opacity":1,"originX":"left","originY":"top","rmpRole":"companyName","version":"6.9.1","visible":true,"fillRule":"nonzero","fontSize":28,"overline":false,"pathSide":"left","direction":"ltr","fontStyle":"normal","pathAlign":"baseline","textAlign":"center","underline":false,"fontFamily":"League Spartan","fontWeight":"bold","lineHeight":1.16,"paintFirst":"fill","charSpacing":0,"linethrough":false,"strokeWidth":1,"strokeLineCap":"butt","strokeUniform":false,"strokeLineJoin":"miter","backgroundColor":"","pathStartOffset":0,"strokeDashArray":null,"strokeDashOffset":0,"strokeMiterLimit":4,"textBackgroundColor":"","textDecorationThickness":66.667,"globalCompositeOperation":"source-over"},{"top":190,"fill":"#ECFDF5","left":180,"text":"Marcus Sterling","type":"IText","angle":0,"flipX":false,"flipY":false,"skewX":0,"skewY":0,"width":151.4796,"height":24.86,"scaleX":1,"scaleY":1,"shadow":null,"stroke":null,"styles":[],"opacity":1,"originX":"left","originY":"top","rmpRole":"name","version":"6.9.1","visible":true,"fillRule":"nonzero","fontSize":22,"overline":false,"pathSide":"left","direction":"ltr","fontStyle":"normal","pathAlign":"baseline","textAlign":"center","underline":false,"fontFamily":"League Spartan","fontWeight":"bold","lineHeight":1.16,"paintFirst":"fill","charSpacing":0,"linethrough":false,"strokeWidth":1,"strokeLineCap":"butt","strokeUniform":false,"strokeLineJoin":"miter","backgroundColor":"","pathStartOffset":0,"strokeDashArray":null,"strokeDashOffset":0,"strokeMiterLimit":4,"textBackgroundColor":"","textDecorationThickness":66.667,"globalCompositeOperation":"source-over"},{"top":222,"fill":"#10B981","left":180,"text":"LEAD LANDSCAPE ARCHITECT","type":"IText","angle":0,"flipX":false,"flipY":false,"skewX":0,"skewY":0,"width":163.122,"height":13.56,"scaleX":1,"scaleY":1,"shadow":null,"stroke":null,"styles":[],"opacity":1,"originX":"left","originY":"top","rmpRole":"title","version":"6.9.1","visible":true,"fillRule":"nonzero","fontSize":12,"overline":false,"pathSide":"left","direction":"ltr","fontStyle":"normal","pathAlign":"baseline","textAlign":"center","underline":false,"fontFamily":"Urbanist","fontWeight":"normal","lineHeight":1.16,"paintFirst":"fill","charSpacing":0,"linethrough":false,"strokeWidth":1,"strokeLineCap":"butt","strokeUniform":false,"strokeLineJoin":"miter","backgroundColor":"","pathStartOffset":0,"strokeDashArray":null,"strokeDashOffset":0,"strokeMiterLimit":4,"textBackgroundColor":"","textDecorationThickness":66.667,"globalCompositeOperation":"source-over"},{"top":275,"fill":"#A7F3D0","left":180,"text":"www.verdantedge.com","type":"IText","angle":0,"flipX":false,"flipY":false,"skewX":0,"skewY":0,"width":180.579,"height":15.82,"scaleX":1,"scaleY":1,"shadow":null,"stroke":null,"styles":[],"opacity":1,"originX":"left","originY":"top","rmpRole":"url","version":"6.9.1","visible":true,"fillRule":"nonzero","fontSize":14,"overline":false,"pathSide":"left","direction":"ltr","fontStyle":"normal","pathAlign":"baseline","textAlign":"center","underline":false,"fontFamily":"Urbanist","fontWeight":"normal","lineHeight":1.16,"paintFirst":"fill","charSpacing":0,"linethrough":false,"strokeWidth":1,"strokeLineCap":"butt","strokeUniform":false,"strokeLineJoin":"miter","backgroundColor":"","pathStartOffset":0,"strokeDashArray":null,"strokeDashOffset":0,"strokeMiterLimit":4,"textBackgroundColor":"","textDecorationThickness":66.667,"globalCompositeOperation":"source-over"},{"top":300,"fill":"#A7F3D0","left":180,"text":"+1 (555) 321-9800","type":"IText","angle":0,"flipX":false,"flipY":false,"skewX":0,"skewY":0,"width":106.029,"height":15.82,"scaleX":1,"scaleY":1,"shadow":null,"stroke":null,"styles":[],"opacity":1,"originX":"left","originY":"top","rmpRole":"phone","version":"6.9.1","visible":true,"fillRule":"nonzero","fontSize":14,"overline":false,"pathSide":"left","direction":"ltr","fontStyle":"normal","pathAlign":"baseline","textAlign":"center","underline":false,"fontFamily":"Urbanist","fontWeight":"normal","lineHeight":1.16,"paintFirst":"fill","charSpacing":0,"linethrough":false,"strokeWidth":1,"strokeLineCap":"butt","strokeUniform":false,"strokeLineJoin":"miter","backgroundColor":"","pathStartOffset":0,"strokeDashArray":null,"strokeDashOffset":0,"strokeMiterLimit":4,"textBackgroundColor":"","textDecorationThickness":66.667,"globalCompositeOperation":"source-over"},{"src":"/storage/brand/logo-placeholder.webp","top":75,"left":380,"type":"Image","width":512,"height":279,"scaleX":0.1953,"scaleY":0.1953,"originX":"center","originY":"center","rmpRole":"logo","version":"6.0.0","crossOrigin":"anonymous"}],"version":"6.9.1","background":"#0B1712"}