{"font":"Space Grotesk","score":9,"style":"Tech Corporate","objects":[{"rx":0,"src":"/storage/templates/banner-006.hero.jpg","top":0,"fill":"#000000","left":0,"type":"Image","angle":0,"width":323,"height":380,"opacity":1,"originX":"left","originY":"top"},{"rx":0,"top":0,"fill":"#0A192F","left":0,"type":"Rect","angle":0,"width":323,"height":380,"opacity":0.85,"originX":"left","originY":"top"},{"rx":0,"src":"/storage/brand/logo-placeholder.webp","top":82,"fill":"#000000","left":161.5,"type":"Image","angle":0,"width":512,"height":279,"scaleX":0.25,"scaleY":0.25,"opacity":1,"originX":"center","originY":"center","rmpRole":"logo"},{"rx":0,"top":135,"fill":"#FFFFFF","left":161.5,"text":"Company Name","type":"IText","angle":0,"width":200,"height":26,"opacity":1,"originX":"center","originY":"top","rmpRole":"companyName","fontSize":18,"textAlign":"center","fontFamily":"Space Grotesk","fontWeight":"bold","lineHeight":1.2,"charSpacing":100},{"rx":0,"top":195,"fill":"#64FFDA","left":161.5,"text":"INNOVATING\nTHE FUTURE","type":"IText","angle":0,"width":280,"height":85,"opacity":1,"originX":"center","originY":"top","fontSize":34,"textAlign":"center","fontFamily":"Space Grotesk","fontWeight":"bold","lineHeight":1.1,"charSpacing":50},{"rx":0,"top":300,"fill":"#E2E8F0","left":161.5,"text":"Scalable solutions for modern B2B teams.","type":"IText","angle":0,"width":280,"height":22,"opacity":1,"originX":"center","originY":"top","fontSize":14,"textAlign":"center","fontFamily":"Space Grotesk","fontWeight":"normal","lineHeight":1.4,"charSpacing":0},{"rx":0,"top":380,"fill":"#64FFDA","left":0,"type":"Rect","angle":0,"width":323,"height":8,"opacity":1,"originX":"left","originY":"top"},{"rx":12,"top":435,"fill":"#F8FAFC","left":31,"type":"Rect","angle":0,"width":261,"height":135,"opacity":1,"originX":"left","originY":"top"},{"rx":0,"top":465,"fill":"#0A192F","left":161.5,"text":"Your Name","type":"IText","angle":0,"width":200,"height":30,"opacity":1,"originX":"center","originY":"top","rmpRole":"name","fontSize":24,"textAlign":"center","fontFamily":"Space Grotesk","fontWeight":"bold","lineHeight":1.2,"charSpacing":0},{"rx":0,"top":500,"fill":"#475569","left":161.5,"text":"Title / Role","type":"IText","angle":0,"width":200,"height":20,"opacity":1,"originX":"center","originY":"top","rmpRole":"title","fontSize":15,"textAlign":"center","fontFamily":"Space Grotesk","fontWeight":"normal","lineHeight":1.2,"charSpacing":20},{"rx":1.5,"top":540,"fill":"#64FFDA","left":161.5,"type":"Rect","angle":0,"width":40,"height":3,"opacity":1,"originX":"center","originY":"center"},{"rx":0,"top":630,"fill":"#0A192F","left":0,"type":"Rect","angle":0,"width":323,"height":130,"opacity":1,"originX":"left","originY":"top"},{"rx":0,"top":658,"fill":"#FFFFFF","left":161.5,"text":"+1 (555) 123-4567","type":"IText","angle":0,"width":200,"height":26,"opacity":1,"originX":"center","originY":"top","rmpRole":"phone","fontSize":20,"textAlign":"center","fontFamily":"Space Grotesk","fontWeight":"bold","lineHeight":1.2,"charSpacing":50},{"rx":0,"top":692,"fill":"#64FFDA","left":161.5,"text":"www.yourcompany.com","type":"IText","angle":0,"width":200,"height":20,"opacity":1,"originX":"center","originY":"top","rmpRole":"url","fontSize":15,"textAlign":"center","fontFamily":"Space Grotesk","fontWeight":"normal","lineHeight":1.2,"charSpacing":20}],"background":"#FFFFFF","imagePrompt":"Abstract dark blue and cyan geometric high-tech background for corporate B2B"}