{"font":"Space Grotesk","score":9,"style":"Dark Tech Corporate","objects":[{"src":"/storage/templates/flyer-004.hero.jpg","top":0,"left":380,"type":"Image","angle":0,"width":380,"height":538,"opacity":1,"originX":"left","originY":"top"},{"rx":0,"top":0,"fill":"#48CAE4","left":380,"type":"Rect","angle":0,"width":380,"height":4,"opacity":1,"originX":"left","originY":"top"},{"rx":0,"top":0,"fill":"#48CAE4","left":0,"type":"Rect","angle":0,"width":80,"height":4,"opacity":1,"originX":"left","originY":"top"},{"src":"/storage/brand/logo-placeholder.webp","top":32,"left":46,"type":"Image","angle":0,"width":512,"height":279,"scaleX":0.14,"scaleY":0.14,"opacity":1,"originX":"left","originY":"top","rmpRole":"logo"},{"top":51,"fill":"#FFFFFF","left":135,"text":"Company Name","type":"IText","angle":0,"opacity":1,"originX":"left","originY":"center","rmpRole":"companyName","fontSize":18,"textAlign":"left","fontFamily":"Space Grotesk","fontWeight":"bold","lineHeight":1,"charSpacing":50},{"rx":0,"top":118,"fill":"#48CAE4","left":46,"type":"Rect","angle":0,"width":6,"height":6,"opacity":1,"originX":"left","originY":"top"},{"top":105,"fill":"#FFFFFF","left":60,"text":"INNOVATIVE\nTECH STRATEGY","type":"IText","angle":0,"opacity":1,"originX":"left","originY":"top","fontSize":30,"textAlign":"left","fontFamily":"Space Grotesk","fontWeight":"bold","lineHeight":1.15,"charSpacing":20},{"top":190,"fill":"#48CAE4","left":46,"text":"Empowering your digital transformation.","type":"IText","angle":0,"opacity":1,"originX":"left","originY":"top","fontSize":14,"textAlign":"left","fontFamily":"Space Grotesk","fontWeight":"normal","lineHeight":1.2,"charSpacing":10},{"top":215,"fill":"#CBD5E1","left":46,"text":"Deliver exceptional results with our\nindustry-leading enterprise solutions.\nDesigned for scalability, security,\nand seamless integration.","type":"IText","angle":0,"opacity":1,"originX":"left","originY":"top","fontSize":12,"textAlign":"left","fontFamily":"Space Grotesk","fontWeight":"normal","lineHeight":1.5,"charSpacing":10},{"rx":8,"top":305,"fill":"#1E293B","left":46,"type":"Rect","angle":0,"width":288,"height":80,"opacity":1,"originX":"left","originY":"top"},{"top":320,"fill":"#FFFFFF","left":118,"text":"10x","type":"IText","angle":0,"opacity":1,"originX":"center","originY":"top","fontSize":32,"textAlign":"center","fontFamily":"Space Grotesk","fontWeight":"bold","lineHeight":1,"charSpacing":0},{"top":358,"fill":"#CBD5E1","left":118,"text":"FASTER DEPLOYMENT","type":"IText","angle":0,"opacity":1,"originX":"center","originY":"top","fontSize":9,"textAlign":"center","fontFamily":"Space Grotesk","fontWeight":"bold","lineHeight":1,"charSpacing":50},{"rx":0,"top":320,"fill":"#334155","left":190,"type":"Rect","angle":0,"width":1,"height":50,"opacity":1,"originX":"left","originY":"top"},{"top":320,"fill":"#FFFFFF","left":262,"text":"24/7","type":"IText","angle":0,"opacity":1,"originX":"center","originY":"top","fontSize":32,"textAlign":"center","fontFamily":"Space Grotesk","fontWeight":"bold","lineHeight":1,"charSpacing":0},{"top":358,"fill":"#CBD5E1","left":262,"text":"GLOBAL SUPPORT","type":"IText","angle":0,"opacity":1,"originX":"center","originY":"top","fontSize":9,"textAlign":"center","fontFamily":"Space Grotesk","fontWeight":"bold","lineHeight":1,"charSpacing":50},{"rx":0,"top":420,"fill":"#1E293B","left":46,"type":"Rect","angle":0,"width":288,"height":1,"opacity":1,"originX":"left","originY":"top"},{"top":445,"fill":"#FFFFFF","left":46,"text":"Your Name","type":"IText","angle":0,"opacity":1,"originX":"left","originY":"top","rmpRole":"name","fontSize":14,"textAlign":"left","fontFamily":"Space Grotesk","fontWeight":"bold","lineHeight":1.2,"charSpacing":0},{"top":465,"fill":"#CBD5E1","left":46,"text":"Title / Role","type":"IText","angle":0,"opacity":1,"originX":"left","originY":"top","rmpRole":"title","fontSize":12,"textAlign":"left","fontFamily":"Space Grotesk","fontWeight":"normal","lineHeight":1.2,"charSpacing":0},{"top":445,"fill":"#FFFFFF","left":334,"text":"+1 (555) 123-4567","type":"IText","angle":0,"opacity":1,"originX":"right","originY":"top","rmpRole":"phone","fontSize":14,"textAlign":"right","fontFamily":"Space Grotesk","fontWeight":"bold","lineHeight":1.2,"charSpacing":0},{"top":465,"fill":"#48CAE4","left":334,"text":"www.yourcompany.com","type":"IText","angle":0,"opacity":1,"originX":"right","originY":"top","rmpRole":"url","fontSize":12,"textAlign":"right","fontFamily":"Space Grotesk","fontWeight":"normal","lineHeight":1.2,"charSpacing":0}],"background":"#0B132B","imagePrompt":"Modern corporate glass office building at night with abstract blue neon light reflections, dark and moody, high-end tech aesthetic."}