{"font":"Manrope","score":9,"style":"Corporate Tech Split","objects":[{"src":"/storage/templates/postcard-019.hero.jpg","top":0,"left":380,"type":"Image","width":380,"height":507,"opacity":1,"originX":"left","originY":"top"},{"top":0,"fill":"#06B6D4","left":375,"type":"Rect","width":5,"height":507,"originX":"left","originY":"top"},{"rx":100,"top":350,"fill":"#06B6D4","left":-50,"type":"Rect","width":200,"height":200,"opacity":0.05,"originX":"left","originY":"top"},{"src":"/storage/brand/logo-placeholder.webp","top":40,"left":46,"type":"Image","width":512,"height":279,"scaleX":0.2,"scaleY":0.2,"originX":"left","originY":"top","rmpRole":"logo"},{"top":115,"fill":"#FFFFFF","left":46,"text":"Company Name","type":"IText","originX":"left","originY":"top","rmpRole":"companyName","fontSize":26,"textAlign":"left","fontFamily":"Manrope","fontWeight":"800","lineHeight":1.2,"charSpacing":10},{"top":210,"fill":"#06B6D4","left":46,"text":"Your Name","type":"IText","originX":"left","originY":"top","rmpRole":"name","fontSize":20,"textAlign":"left","fontFamily":"Manrope","fontWeight":"700","lineHeight":1.2,"charSpacing":0},{"top":240,"fill":"#94A3B8","left":46,"text":"Title / Role","type":"IText","originX":"left","originY":"top","rmpRole":"title","fontSize":14,"textAlign":"left","fontFamily":"Manrope","fontWeight":"400","lineHeight":1.2,"charSpacing":10},{"rx":1,"top":280,"fill":"#06B6D4","left":46,"type":"Rect","width":40,"height":3,"originX":"left","originY":"top"},{"top":395,"fill":"#F8FAFC","left":46,"text":"+1 (555) 123-4567","type":"IText","originX":"left","originY":"top","rmpRole":"phone","fontSize":14,"textAlign":"left","fontFamily":"Manrope","fontWeight":"500","lineHeight":1.4,"charSpacing":10},{"top":425,"fill":"#F8FAFC","left":46,"text":"www.yourcompany.com","type":"IText","originX":"left","originY":"top","rmpRole":"url","fontSize":14,"textAlign":"left","fontFamily":"Manrope","fontWeight":"500","lineHeight":1.4,"charSpacing":10}],"background":"#0A0F1C","imagePrompt":"Abstract blue and cyan glowing neon fiber optics or digital data streams on dark background, high contrast, tech corporate style"}